version_manager/__init__.py
version_manager/__main__.py
version_manager/command_current_version.py
version_manager/command_version_list.py
version_manager/custom/custom_pattern.py
version_manager/custom/custom_pattern_definition.py
version_manager/custom/custom_settings.py
version_manager/matcher_builder.py
version_manager/matchers/__init__.py
version_manager/matchers/array_pattern.py
version_manager/matchers/match_counter.py
version_manager/matchers/maven_pattern.py
version_manager/matchers/pattern.py
version_manager/matchers/regex_pattern.py
version_manager/matchers/string_pattern.py
version_manager/options_set.py
version_manager/parse_version.py
version_manager/py.typed
version_manager/settings_reader.py
version_manager/tests/__init__.py
version_manager/tests/test_maven_pattern.py
version_manager/tests/test_regex_pattern.py
version_manager/util_find.py
vm-2022.11.1.dist-info/entry_points.txt
vm-2022.11.1.dist-info/WHEEL
vm-2022.11.1.dist-info/METADATA
vm-2022.11.1.dist-info/RECORD
