Metadata-Version: 2.1
Name: vm
Version: 2022.11.1
Summary: version manager manages versions and patches files
License: BSD
Author: Bogdan Mustiata
Author-email: bogdan.mustiata@gmail.com
Requires-Python: >=3.7,<4.0
Classifier: License :: Other/Proprietary License
Classifier: Programming Language :: Python :: 3
Classifier: Programming Language :: Python :: 3.7
Classifier: Programming Language :: Python :: 3.8
Classifier: Programming Language :: Python :: 3.9
Classifier: Programming Language :: Python :: 3.10
Classifier: Programming Language :: Python :: 3.11
Requires-Dist: PyYAML (==6.0)
Requires-Dist: colorama (==0.4.6)
Requires-Dist: termcolor-util (==2022.11.1)
